pte_adapter_model_explorer/__init__.py
pte_adapter_model_explorer/constants.py
pte_adapter_model_explorer/extended_header.py
pte_adapter_model_explorer/main.py
pte_adapter_model_explorer/builder/__init__.py
pte_adapter_model_explorer/builder/builder.py
pte_adapter_model_explorer/builder/delegate.py
pte_adapter_model_explorer/builder/instruction.py
pte_adapter_model_explorer/builder/metadata.py
pte_adapter_model_explorer/builder/util.py
pte_adapter_model_explorer/delegates/__init__.py
pte_adapter_model_explorer/delegates/ethosu.py
pte_adapter_model_explorer/delegates/vgf.py
pte_adapter_model_explorer/delegates/xnnpack.py
pte_adapter_model_explorer/executorch_flatbuffer/__init__.py
pte_adapter_model_explorer/executorch_flatbuffer/program_generated.py
pte_adapter_model_explorer/executorch_flatbuffer/scalar_type_generated.py
pte_adapter_model_explorer/executorch_flatbuffer/xnnpack_generated.py
pte_adapter_model_explorer/schema/LICENSE
pte_adapter_model_explorer/schema/program.fbs
pte_adapter_model_explorer/schema/scalar_type.fbs
pte_adapter_model_explorer/schema/xnnpack.fbs
pte_adapter_model_explorer/tests/__init__.py
pte_adapter_model_explorer/tests/test_e2e.py
pte_adapter_model_explorer/tests/test_extended_header.py
pte_adapter_model_explorer/tests/test_model_explorer_cli.py
pte_adapter_model_explorer-0.1.0.dist-info/licenses/LICENSE
pte_adapter_model_explorer-0.1.0.dist-info/METADATA
pte_adapter_model_explorer-0.1.0.dist-info/WHEEL
pte_adapter_model_explorer-0.1.0.dist-info/top_level.txt
pte_adapter_model_explorer-0.1.0.dist-info/RECORD
