Metadata-Version: 2.4
Name: pte-adapter-model-explorer
Version: 0.1.0
Summary: Adapter for Model Explorer to support PTE files for Ethos-U and VGF targets
License: LICENSING NOTICE
Project-URL: Repository, https://github.com/arm/pte-adapter-model-explorer
Keywords: model-explorer,ethos,pte,visualization
Classifier: Development Status :: 4 - Beta
Classifier: Intended Audience :: Developers
Classifier: Operating System :: POSIX :: Linux
Classifier: Programming Language :: Python :: 3.10
Classifier: Programming Language :: Python :: 3.11
Classifier: Programming Language :: Python :: 3.12
Requires-Python: <3.13,>=3.10
License-File: LICENSE
Requires-Dist: ai-edge-model-explorer<0.2.0,>=0.1.28
Requires-Dist: vgf-adapter-model-explorer==0.4.1
Requires-Dist: tosa-adapter-model-explorer==0.1.0
Requires-Dist: flatbuffers>25.9
Dynamic: license-file
